{
    "common": {
      "name": "countdown",
      "version": "1.0.9",
      "news": {
        "1.1.0": {
          "en": "Bugfix readme link",
          "de": "Bugfix Readme Link",
          "ru": "Исправлена ссылка на readme",
          "pt": "Link Leiame do Bugfix",
          "nl": "Leesmij-link voor bugfix",
          "fr": "Lien Readme du correctif",
          "it": "Link readme bugfix",
          "es": "Enlace Léame de corrección de errores",
          "pl": "Link do pliku Readme poprawki",
          "zh-cn": "错误修正自述链接"
      },
        "1.0.9": {
          "en": "Bugfix log messages",
          "de": "Bugfix-Protokollmeldungen",
          "ru": "Исправление сообщений журнала",
          "pt": "Mensagens de log de correções",
          "nl": "Bugfix-logberichten",
          "fr": "Messages du journal de correction de bogues",
          "it": "Messaggi di registro bugfix",
          "es": "Mensajes de registro de corrección de errores",
          "pl": "Komunikaty dziennika błędów",
          "zh-cn": "错误修正日志消息"
      },
        "1.0.8": {
          "en": "Repeat countdown in defined period (e.g. every year)",
          "de": "Wiederholen Sie den Countdown in einem definierten Zeitraum (z. B. jedes Jahr).",
          "ru": "Повторите обратный отсчет в определенный период (например, каждый год)",
          "pt": "Repita a contagem regressiva no período definido (por exemplo, todos os anos)",
          "nl": "Herhaal het aftellen in een bepaalde periode (bijv. Elk jaar)",
          "fr": "Répéter le compte à rebours dans la période définie (par exemple chaque année)",
          "it": "Ripeti il conto alla rovescia in un periodo definito (ad es. Ogni anno)",
          "es": "Repita la cuenta regresiva en un período definido (por ejemplo, cada año)",
          "pl": "Powtórz odliczanie w zdefiniowanym okresie (np. Co roku)",
          "zh-cn": "在定义的时间段内（例如每年）重复倒数计时"
      },
        "1.0.7": {
          "en": "Added date format YYYY-MM-DD",
          "de": "Datumsformat hinzugefügt JJJJ-MM-TT",
          "ru": "Добавлен формат даты ГГГГ-ММ-ДД",
          "pt": "Formato de data adicionado AAAA-MM-DD",
          "nl": "Datumformaat toegevoegd JJJJ-MM-DD",
          "fr": "Format de date ajouté AAAA-MM-JJ",
          "it": "Aggiunto il formato della data AAAA-MM-GG",
          "es": "Formato de fecha agregado AAAA-MM-DD",
          "pl": "Dodano format daty RRRR-MM-DD",
          "zh-cn": "添加日期格式YYYY-MM-DD"
      },
        "1.0.6": {
          "en": "DutchmanNL: Fixed adapter type",
          "de": "DutchmanNL: Adaptertyp behoben",
          "ru": "DutchmanNL: фиксированный тип адаптера",
          "pt": "DutchmanNL: tipo de adaptador fixo",
          "nl": "DutchmanNL: Type vaste adapter",
          "fr": "DutchmanNL: Type d'adaptateur fixe",
          "it": "DutchmanNL: tipo di adattatore fisso",
          "es": "DutchmanNL: tipo de adaptador fijo",
          "pl": "DutchmanNL: Naprawiono typ adaptera",
          "zh-cn": "DutchmanNL：固定适配器类型"
      },
        "1.0.5": {
          "en": "Bugfix for countdown around midnight",
          "de": "Bugfix für Countdown gegen Mitternacht",
          "ru": "Исправлена ошибка обратного отсчета около полуночи",
          "pt": "Correção de bug para contagem regressiva por volta da meia-noite",
          "nl": "Bugfix voor aftellen rond middernacht",
          "fr": "Correction d'un bug pour le compte à rebours vers minuit",
          "it": "Bugfix per il conto alla rovescia verso mezzanotte",
          "es": "Corrección de errores para la cuenta regresiva alrededor de la medianoche",
          "pl": "Bugfix do odliczania około północy",
          "zh-cn": "午夜时分倒计时的错误修正"
      },
        "1.0.4": {
            "en": "Change in release infos",
            "de": "Änderung der Release-Infos",
            "ru": "Изменение в выпуске информации",
            "pt": "Alterar as informações de lançamento",
            "nl": "Wijziging in release-info",
            "fr": "Changement dans les infos de sortie",
            "it": "Modifica delle informazioni sulla versione",
            "es": "Cambio en la información de lanzamiento",
            "pl": "Zmiana informacji o wydaniu",
            "zh-cn": "更新发布信息"
        },
        "1.0.3": {
          "en": "Changes for Compact Mode, allow multiple instances",
          "de": "Änderungen für den Kompaktmodus, mehrere Instanzen erlauben",
          "ru": "Изменения в компактном режиме, позволяют несколько экземпляров",
          "pt": "Alterações para o modo compacto, permitem várias instâncias",
          "nl": "Wijzigingen voor de compacte modus, staan meerdere instanties toe",
          "fr": "Modifications pour le mode compact, autoriser plusieurs instances",
          "it": "Modifiche per la modalità compatta, consentono più istanze",
          "es": "Cambios para el modo compacto, permitir múltiples instancias",
          "pl": "Zmiany w trybie kompaktowym pozwalają na wiele wystąpień",
          "zh-cn": "紧凑模式的更改，允许多个实例"
        },
        "1.0.2": {
          "en": "Release Version",
          "de": "Veröffentlichungsversion",
          "ru": "Версия выпуска",
          "pt": "Versão de lançamento",
          "nl": "Uitgegeven versie",
          "fr": "Version finale",
          "it": "Versione di rilascio",
          "es": "Versión de lanzamiento",
          "pl": "Wersja wydania",
          "zh-cn": "发行版"
        },
        "0.7.0": {
          "en": "Bugfixes, add countdowns with addhours and addminutes",
          "de": "Bugfixes, Countdowns mit Addhours und Addminutes",
          "ru": "Исправления ошибок, добавление обратного отсчета с помощью addhours и addminutes",
          "pt": "Correções de bugs, adicionar contagens regressivas com addhours e addminutes",
          "nl": "Bugfixes, voeg countdowns toe met addhours en addminutes",
          "fr": "Correction de bugs, ajouter des comptes à rebours avec addhours et addminutes",
          "it": "Correzioni di bug, aggiungere conti alla rovescia con addhours e addminute",
          "es": "Corrección de errores, agregue cuentas regresivas con horas adicionales y minutos adicionales",
          "pl": "Poprawki błędów, dodawanie odliczania z godzinami i minutami",
          "zh-cn": "错误修正，添加addhours和addminutes倒计时"
        },
        "0.6.0": {
          "en": "Adjustable date format, Add Countdowns with adddays",
          "de": "Einstellbares Datumsformat, Countdowns mit adddays hinzufügen",
          "ru": "Настраиваемый формат даты, Добавить обратный отсчет с дополнениями",
          "pt": "Formato de data ajustável, adicionar contagens com adddays",
          "nl": "Aanpasbare datumnotatie, Countdowns toevoegen met adddays",
          "fr": "Format de date ajustable, Ajouter des comptes à rebours avec adddays",
          "it": "Formato data regolabile, Aggiungi conti alla rovescia con giorni aggiuntivi",
          "es": "Formato de fecha ajustable, agregar cuentas regresivas con adddays",
          "pl": "Regulowany format daty, dodaj odliczanie z dodatkowymi dniami",
          "zh-cn": "可调整的日期格式，使用adddays添加倒计时"
        },
        "0.5.0": {
          "en": "Adjustable Tabel",
          "de": "Einstellbare Tabelle",
          "ru": "Регулируемая Табель",
          "pt": "Tabel Ajustável",
          "nl": "Verstelbare tabel",
          "fr": "Tabel Réglable",
          "it": "Tabel regolabile",
          "es": "Tabel ajustable",
          "pl": "Tabel regulowany",
          "zh-cn": "可调节的表格"
        },
        "0.4.0": {
          "en": "Restructuring",
          "de": "Umstrukturierung",
          "ru": "реструктурирование",
          "pt": "Reestruturação",
          "nl": "herstructurering",
          "fr": "Restructuration",
          "it": "ristrutturazione",
          "es": "Reestructuración",
          "pl": "Restrukturyzacja",
          "zh-cn": "重组"
        },
        "0.3.0": {
          "en": "Add total Hours and Days, small fixes",
          "de": "Totale Stunden und Tage hinzugefügt, kleine Korrekturen",
          "ru": "Добавьте общее количество часов и дней, небольшие исправления",
          "pt": "Adicionar total de horas e dias, pequenas correções",
          "nl": "Voeg totale uren en dagen toe, kleine aanpassingen",
          "fr": "Ajouter le nombre total d’heures et de jours, petites corrections",
          "it": "Aggiungi ore e giorni totali, piccole correzioni",
          "es": "Agregar horas y días totales, pequeñas correcciones",
          "pl": "Dodaj całkowitą liczbę godzin i dni, małe poprawki",
          "zh-cn": "添加总小时数和天数，小修正"
      },
        "0.2.0": {
          "en": "Ajusted packages",
          "de": "Pakete angepasst",
          "ru": "Скорректированные пакеты",
          "pt": "Pacotes Ajustados",
          "nl": "Aangepaste pakketten",
          "fr": "Forfaits ajustés",
          "it": "Pacchetti aggiustati",
          "es": "Paquetes ajustados",
          "pl": "Dostosowane pakiety",
          "zh-cn": "Ajusted包"
      },
        "0.1.0": {
          "en": "Initial version",
          "de": "Erste Version",
          "ru": "Первоначальная версия",
          "pt": "Versão inicial",
          "nl": "Eerste versie",
          "fr": "Version initiale",
          "it": "Versione iniziale",
          "es": "Versión inicial",
          "pl": "Początkowa wersja",
          "zh-cn": "初始版本"
        }    
      },
      "title": "Countdown",
          "titleLang": {
            "en": "Countdown",
            "de": "Countdown",
            "ru": "обратный отсчет",
            "pt": "Contagem regressiva",
            "nl": "Countdown",
            "fr": "Compte à rebours",
            "it": "Conto alla rovescia",
            "es": "cuenta regresiva",
            "pl": "Odliczanie",
            "zh-cn": "倒数"
          },
          "desc": {
            "en": "Countdown Adapter",
            "de": "Countdown Adapter",
            "ru": "Адаптер обратного отсчета",
            "pt": "Adaptador de Contagem Regressiva",
            "nl": "Afteladapter",
            "fr": "Adaptateur compte à rebours",
            "it": "Conto alla rovescia",
            "es": "Adaptador de cuenta regresiva",
            "pl": "Adapter do odliczania",
            "zh-cn": "倒计时适配器"
          },
          "authors": [
              "Jack <blacksonj7@gmail.com>"
          ],
          "license":                  "MIT",
          "platform":                 "Javascript/Node.js",
          "mode":                     "daemon",
          "messagebox":               true,
          "enabled":                  true,
          "compact": true,
          "readme":                   "https://github.com/jack-blackson/ioBroker.countdown/blob/master/README.md",
          "loglevel":                 "info",     
          "keywords":                 ["countdown"],
          "icon":                     "countdown.png",
          "materialize":              true,
          "extIcon":                  "https://raw.githubusercontent.com/jack-blackson/ioBroker.countdown/master/admin/countdown.png",
          "type":                     "misc-data",
      "singletonHost":            false
      },
       "native": {
          "interval": 120000,
          "autodelete": false,
          "dateformat": "DD.MM.YYYY HH:MM",
          "inWordsShort": false,
          "inWordsLong": true,
          "totalNoOfDays":false,
          "totalNoOfHours":false,
          "totalNoOfWeeks":false,
          "endDate":true
      },
      "objects": [],
      "instanceObjects": []
  }
